{
  "id": "6b0a281c-f613-49f8-9a90-a1b3bea59551",
  "prevId": "2b13b415-0d4d-4083-b5d7-550e7da647d8",
  "version": "5",
  "dialect": "pg",
  "tables": {
    "entry": {
      "name": "entry",
      "schema": "",
      "columns": {
        "id": {
          "name": "id",
          "type": "serial",
          "primaryKey": true,
          "notNull": true
        },
        "description": {
          "name": "description",
          "type": "varchar(100)",
          "primaryKey": false,
          "notNull": false
        },
        "start_time": {
          "name": "start_time",
          "type": "timestamp",
          "primaryKey": false,
          "notNull": false,
          "default": "now()"
        },
        "end_time": {
          "name": "end_time",
          "type": "timestamp",
          "primaryKey": false,
          "notNull": false
        },
        "duration": {
          "name": "duration",
          "type": "bigint",
          "primaryKey": false,
          "notNull": false,
          "default": 0
        },
        "billable_rate": {
          "name": "billable_rate",
          "type": "bigint",
          "primaryKey": false,
          "notNull": false,
          "default": 0
        },
        "user_id": {
          "name": "user_id",
          "type": "varchar",
          "primaryKey": false,
          "notNull": true
        },
        "project_id": {
          "name": "project_id",
          "type": "serial",
          "primaryKey": false,
          "notNull": true
        }
      },
      "indexes": {},
      "foreignKeys": {
        "entry_user_id_auth_user_id_fk": {
          "name": "entry_user_id_auth_user_id_fk",
          "tableFrom": "entry",
          "tableTo": "auth_user",
          "columnsFrom": [
            "user_id"
          ],
          "columnsTo": [
            "id"
          ],
          "onDelete": "cascade",
          "onUpdate": "no action"
        },
        "entry_project_id_project_id_fk": {
          "name": "entry_project_id_project_id_fk",
          "tableFrom": "entry",
          "tableTo": "project",
          "columnsFrom": [
            "project_id"
          ],
          "columnsTo": [
            "id"
          ],
          "onDelete": "set null",
          "onUpdate": "no action"
        }
      },
      "compositePrimaryKeys": {},
      "uniqueConstraints": {}
    },
    "user_key": {
      "name": "user_key",
      "schema": "",
      "columns": {
        "id": {
          "name": "id",
          "type": "varchar(255)",
          "primaryKey": true,
          "notNull": true
        },
        "user_id": {
          "name": "user_id",
          "type": "varchar(15)",
          "primaryKey": false,
          "notNull": true
        },
        "hashed_password": {
          "name": "hashed_password",
          "type": "varchar(255)",
          "primaryKey": false,
          "notNull": false
        }
      },
      "indexes": {},
      "foreignKeys": {
        "user_key_user_id_auth_user_id_fk": {
          "name": "user_key_user_id_auth_user_id_fk",
          "tableFrom": "user_key",
          "tableTo": "auth_user",
          "columnsFrom": [
            "user_id"
          ],
          "columnsTo": [
            "id"
          ],
          "onDelete": "no action",
          "onUpdate": "no action"
        }
      },
      "compositePrimaryKeys": {},
      "uniqueConstraints": {}
    },
    "project": {
      "name": "project",
      "schema": "",
      "columns": {
        "id": {
          "name": "id",
          "type": "serial",
          "primaryKey": true,
          "notNull": true
        },
        "name": {
          "name": "name",
          "type": "varchar(100)",
          "primaryKey": false,
          "notNull": false
        },
        "user_id": {
          "name": "user_id",
          "type": "varchar",
          "primaryKey": false,
          "notNull": true
        }
      },
      "indexes": {},
      "foreignKeys": {
        "project_user_id_auth_user_id_fk": {
          "name": "project_user_id_auth_user_id_fk",
          "tableFrom": "project",
          "tableTo": "auth_user",
          "columnsFrom": [
            "user_id"
          ],
          "columnsTo": [
            "id"
          ],
          "onDelete": "cascade",
          "onUpdate": "no action"
        }
      },
      "compositePrimaryKeys": {},
      "uniqueConstraints": {}
    },
    "user_session": {
      "name": "user_session",
      "schema": "",
      "columns": {
        "id": {
          "name": "id",
          "type": "varchar(128)",
          "primaryKey": true,
          "notNull": true
        },
        "user_id": {
          "name": "user_id",
          "type": "varchar(15)",
          "primaryKey": false,
          "notNull": true
        },
        "active_expires": {
          "name": "active_expires",
          "type": "bigint",
          "primaryKey": false,
          "notNull": true
        },
        "idle_expires": {
          "name": "idle_expires",
          "type": "bigint",
          "primaryKey": false,
          "notNull": true
        }
      },
      "indexes": {},
      "foreignKeys": {
        "user_session_user_id_auth_user_id_fk": {
          "name": "user_session_user_id_auth_user_id_fk",
          "tableFrom": "user_session",
          "tableTo": "auth_user",
          "columnsFrom": [
            "user_id"
          ],
          "columnsTo": [
            "id"
          ],
          "onDelete": "no action",
          "onUpdate": "no action"
        }
      },
      "compositePrimaryKeys": {},
      "uniqueConstraints": {}
    },
    "auth_user": {
      "name": "auth_user",
      "schema": "",
      "columns": {
        "id": {
          "name": "id",
          "type": "varchar(15)",
          "primaryKey": true,
          "notNull": true
        },
        "username": {
          "name": "username",
          "type": "varchar",
          "primaryKey": false,
          "notNull": false
        }
      },
      "indexes": {},
      "foreignKeys": {},
      "compositePrimaryKeys": {},
      "uniqueConstraints": {}
    }
  },
  "enums": {},
  "schemas": {},
  "_meta": {
    "schemas": {},
    "tables": {},
    "columns": {}
  }
}